setup.py
ProbabilityDistributions/Binomialdistribution.py
ProbabilityDistributions/Gaussiandistribution.py
ProbabilityDistributions/Generaldistribution.py
ProbabilityDistributions/__init__.py
ProbabilityDistributions.egg-info/PKG-INFO
ProbabilityDistributions.egg-info/SOURCES.txt
ProbabilityDistributions.egg-info/dependency_links.txt
ProbabilityDistributions.egg-info/not-zip-safe
ProbabilityDistributions.egg-info/top_level.txt