Metadata-Version: 1.0
Name: ProbabilityDistributions
Version: 1.0
Summary: Gaussian Binomial distributions
Home-page: UNKNOWN
Author: Pankhil prajapati
Author-email: puruprajapti8@gmail.com
License: UNKNOWN
Platform: UNKNOWN
